{
  "page": 1,
  "results": [
    {
      "id": 1025125,
      "type": "movie",
      "rating": "7.5",
      "release_date": "Sep 12, 2024",
      "last_air_date": null,
      "lang": "ml",
      "description": "Strange events unfold in a monkey-inhabited village, drive a newlywed couple and forest officials to embark on a mission to uncover the root cause of the unusual disturbances.",
      "title": "Kishkindha Kaandam",
      "images": {
        "coverSmall": "http://image.tmdb.org/t/p/w342/rniBYHDRs6e8qMkPr4D4ZE5uMhF.jpg",
        "coverMedium": "http://image.tmdb.org/t/p/w780/rniBYHDRs6e8qMkPr4D4ZE5uMhF.jpg",
        "coverLarge": "http://image.tmdb.org/t/p/w780/rniBYHDRs6e8qMkPr4D4ZE5uMhF.jpg",
        "bannerSmall": "http://image.tmdb.org/t/p/w780/g1Jm4xnRkzqtFNgLvwBvKrBHD7w.jpg",
        "bannerLarge": "http://image.tmdb.org/t/p/w1280/g1Jm4xnRkzqtFNgLvwBvKrBHD7w.jpg",
        "logo": null
      },
      "isAdult": false
    },
    {
      "id": 1134223,
      "type": "movie",
      "rating": "6.0",
      "release_date": "Jun 7, 1994",
      "last_air_date": null,
      "lang": "te",
      "description": "Bhetalam hides stolen gold in a cemetery and before dying, he confesses his sin to a group of travellers. Each individual tries to beat the other in the race to find the fortune.",
      "title": "Kishkinda Kaanda",
      "images": {
        "coverSmall": "http://image.tmdb.org/t/p/w342/6Vafko0gAMNhjIbw6kBEVjQCJI3.jpg",
        "coverMedium": "http://image.tmdb.org/t/p/w780/6Vafko0gAMNhjIbw6kBEVjQCJI3.jpg",
        "coverLarge": "http://image.tmdb.org/t/p/w780/6Vafko0gAMNhjIbw6kBEVjQCJI3.jpg",
        "bannerSmall": "http://image.tmdb.org/t/p/w780null",
        "bannerLarge": "http://image.tmdb.org/t/p/w1280null",
        "logo": null
      },
      "isAdult": false
    }
  ],
  "total_pages": 1,
  "total_results": 2
}
